amisproxy/__init__.py
amisproxy/admin.py
amisproxy/apps.py
amisproxy/models.py
amisproxy/tests.py
amisproxy/urls.py
amisproxy/views.py
amisproxy/migrations/__init__.py
django_amisproxy-0.3.0.dist-info/licenses/LICENSE
django_amisproxy-0.3.0.dist-info/METADATA
django_amisproxy-0.3.0.dist-info/WHEEL
django_amisproxy-0.3.0.dist-info/top_level.txt
django_amisproxy-0.3.0.dist-info/RECORD
