Metadata-Version: 2.4
Name: django-amisproxy
Version: 0.3.0
Summary: Add your description here
Author-email: liuli <525334480@qq.com>
Maintainer-email: liuli <525334480@qq.com>
License:                                  Apache License
Project-URL: homepage, https://github.com/liuli01/django_amisproxy
Project-URL: documentation, https://github.com/liuli01/django_amisproxy
Project-URL: repository, https://github.com/liuli01/django_amisproxy
Project-URL: changelog, https://github.com/liuli01/django_amisproxy/releases
Requires-Python: >=3.12
License-File: LICENSE
Requires-Dist: django>=5.2
Requires-Dist: djangorestframework>=3.16.0
Requires-Dist: requests>=2.32.3
Dynamic: license-file
